easwin/__init__.py
easwin-1.0.0.dist-info/licenses/LICENCE
easwin-1.0.0.dist-info/METADATA
easwin-1.0.0.dist-info/WHEEL
easwin-1.0.0.dist-info/top_level.txt
easwin-1.0.0.dist-info/RECORD
